response_checker/__init__.py
response_checker/example.py
response_checker/response_checker.py
response_checker-0.1.dist-info/METADATA
response_checker-0.1.dist-info/WHEEL
response_checker-0.1.dist-info/top_level.txt
response_checker-0.1.dist-info/RECORD
