Metadata-Version: 2.1
Name: response-checker
Version: 0.1
Summary: Package request validation in unit-tests
Home-page: UNKNOWN
Author: Anton Igin
Author-email: example@mail.com
License: UNKNOWN
Platform: UNKNOWN
Classifier: Programming Language :: Python :: 3
Requires-Python: >=3.5
